README.md
setup.py
koala_poder/__init__.py
koala_poder/koala.py
koala_poder.egg-info/PKG-INFO
koala_poder.egg-info/SOURCES.txt
koala_poder.egg-info/dependency_links.txt
koala_poder.egg-info/top_level.txt