Metadata-Version: 2.1
Name: koala-poder
Version: 0.1.2
Summary: A Python Library for generating sentences and doing math with koalas
Author: Blake Peterson
